{
    "id":  "3",
    "name":  "OBSCURA LEATHER JACKET",
    "slug":  "obscura-leather-jacket",
    "price":  549,
    "originalPrice":  699,
    "category":  "jackets",
    "sizes":  [
                  {
                      "name":  "S",
                      "available":  true
                  },
                  {
                      "name":  "M",
                      "available":  true
                  },
                  {
                      "name":  "L",
                      "available":  true
                  },
                  {
                      "name":  "XL",
                      "available":  false
                  }
              ],
    "inStock":  true,
    "isFeatured":  true,
    "isBestseller":  true,
    "rating":  5.0,
    "shortDescription":  "Р В РІР‚В Р РЋРІР‚С™Р В Р’В°Р В Р’В»Р РЋРІР‚вЂњР В РІвЂћвЂ“Р РЋР С“Р РЋР Р‰Р В РЎвЂќР В Р’В° Р РЋРІвЂљВ¬Р В РЎвЂќР РЋРІР‚вЂњР РЋР вЂљР В Р’В° Р В РЎвЂ”Р В РЎвЂўР В Р вЂ Р В Р вЂ¦Р В РЎвЂўР В РЎвЂ“Р В РЎвЂў Р В Р’В·Р В Р’ВµР РЋР вЂљР В Р вЂ¦Р В Р’В° Р В Р’В· Р В РЎВР В Р’В°Р РЋРІР‚С™Р В РЎвЂўР В Р вЂ Р В РЎвЂР В РЎВ Р В РЎвЂ”Р В РЎвЂўР В РЎвЂќР РЋР вЂљР В РЎвЂР РЋРІР‚С™Р РЋРІР‚С™Р РЋР РЏР В РЎВ",
    "description":  "Р В РЎв„ўР РЋРЎвЂњР РЋР вЂљР РЋРІР‚С™Р В РЎвЂќР В Р’В° Obscura Leather Jacket Р Р†Р вЂљРІР‚Сњ Р РЋР С“Р В Р вЂ Р РЋРІР‚вЂњР В РўвЂР РЋРІР‚РЋР В Р’ВµР В Р вЂ¦Р В Р вЂ¦Р РЋР РЏ Р В Р вЂ Р В РЎвЂР РЋРІР‚С™Р В РЎвЂўР В Р вЂ¦Р РЋРІР‚РЋР В Р’ВµР В Р вЂ¦Р В РЎвЂўР РЋРІР‚вЂќ Р В РЎВР В Р’В°Р В РІвЂћвЂ“Р РЋР С“Р РЋРІР‚С™Р В Р’ВµР РЋР вЂљР В Р вЂ¦Р В РЎвЂўР РЋР С“Р РЋРІР‚С™Р РЋРІР‚вЂњ. Р В РІР‚в„ўР В РЎвЂР В РЎвЂ“Р В РЎвЂўР РЋРІР‚С™Р В РЎвЂўР В Р вЂ Р В Р’В»Р В Р’ВµР В Р вЂ¦Р В Р’В° Р В Р’В· Р РЋРІР‚вЂњР РЋРІР‚С™Р В Р’В°Р В Р’В»Р РЋРІР‚вЂњР В РІвЂћвЂ“Р РЋР С“Р РЋР Р‰Р В РЎвЂќР В РЎвЂўР РЋРІР‚вЂќ Р РЋРІвЂљВ¬Р В РЎвЂќР РЋРІР‚вЂњР РЋР вЂљР В РЎвЂ Р В РЎвЂ”Р В РЎвЂўР В Р вЂ Р В Р вЂ¦Р В РЎвЂўР В РЎвЂ“Р В РЎвЂў Р В Р’В·Р В Р’ВµР РЋР вЂљР В Р вЂ¦Р В Р’В° Р В Р’В· Р В РЎВР В Р’В°Р РЋРІР‚С™Р В РЎвЂўР В Р вЂ Р В РЎвЂР В РЎВ Р В РЎвЂ”Р В РЎвЂўР В РЎвЂќР РЋР вЂљР В РЎвЂР РЋРІР‚С™Р РЋРІР‚С™Р РЋР РЏР В РЎВ, Р В РЎВР В Р’В°Р РЋРІР‚Сњ Р В Р’В°Р РЋР С“Р В РЎвЂР В РЎВР В Р’ВµР РЋРІР‚С™Р РЋР вЂљР В РЎвЂР РЋРІР‚РЋР В Р вЂ¦Р РЋРІР‚вЂњ Р В Р’В±Р В Р’В»Р В РЎвЂР РЋР С“Р В РЎвЂќР В Р’В°Р В Р вЂ Р В РЎвЂќР В РЎвЂ, Р В РЎвЂ”Р РЋР вЂљР В РЎвЂР РЋРІР‚В¦Р В РЎвЂўР В Р вЂ Р В Р’В°Р В Р вЂ¦Р РЋРЎвЂњ Р В Р вЂ Р В Р вЂ¦Р РЋРЎвЂњР РЋРІР‚С™Р РЋР вЂљР РЋРІР‚вЂњР РЋРІвЂљВ¬Р В Р вЂ¦Р РЋР вЂ№ Р В РЎвЂќР В РЎвЂР РЋРІвЂљВ¬Р В Р’ВµР В Р вЂ¦Р РЋР вЂ№ Р РЋРІР‚С™Р В Р’В° Р РЋРІР‚С›Р РЋРІР‚вЂњР РЋР вЂљР В РЎВР В РЎвЂўР В Р вЂ Р РЋРЎвЂњ Р В РЎвЂќР РЋР вЂљР В РЎвЂР В Р вЂ Р В Р’В°Р В Р вЂ Р В РЎвЂў-Р РЋРІР‚РЋР В Р’ВµР РЋР вЂљР В Р вЂ Р В РЎвЂўР В Р вЂ¦Р РЋРЎвЂњ Р В РЎвЂ”Р РЋРІР‚вЂњР В РўвЂР В РЎвЂќР В Р’В»Р В Р’В°Р В РўвЂР В РЎвЂќР РЋРЎвЂњ. Р В РЎв„ўР В РЎвЂўР В Р’В¶Р В Р вЂ¦Р В Р’В° Р В РЎвЂќР РЋРЎвЂњР РЋР вЂљР РЋРІР‚С™Р В РЎвЂќР В Р’В° Р В Р вЂ¦Р В Р’В°Р В Р’В±Р РЋРЎвЂњР В Р вЂ Р В Р’В°Р РЋРІР‚Сњ Р РЋРЎвЂњР В Р вЂ¦Р РЋРІР‚вЂњР В РЎвЂќР В Р’В°Р В Р’В»Р РЋР Р‰Р В Р вЂ¦Р В РЎвЂўР РЋРІР‚вЂќ Р В РЎвЂ”Р В Р’В°Р РЋРІР‚С™Р В РЎвЂР В Р вЂ¦Р В РЎвЂ Р В Р’В· Р РЋРІР‚РЋР В Р’В°Р РЋР С“Р В РЎвЂўР В РЎВ, Р РЋР С“Р РЋРІР‚С™Р В Р’В°Р РЋР вЂ№Р РЋРІР‚РЋР В РЎвЂ Р В РЎвЂ”Р В РЎвЂў-Р РЋР С“Р В РЎвЂ”Р РЋР вЂљР В Р’В°Р В Р вЂ Р В Р’В¶Р В Р вЂ¦Р РЋР Р‰Р В РЎвЂўР В РЎВР РЋРЎвЂњ Р В Р вЂ Р В Р’В°Р РЋРІвЂљВ¬Р В РЎвЂўР РЋР вЂ№.",
    "details":  [
                    "Р В РІР‚В Р РЋРІР‚С™Р В Р’В°Р В Р’В»Р РЋРІР‚вЂњР В РІвЂћвЂ“Р РЋР С“Р РЋР Р‰Р В РЎвЂќР В Р’В° Р РЋРІвЂљВ¬Р В РЎвЂќР РЋРІР‚вЂњР РЋР вЂљР В Р’В° Р В РЎвЂ”Р В РЎвЂўР В Р вЂ Р В Р вЂ¦Р В РЎвЂўР В РЎвЂ“Р В РЎвЂў Р В Р’В·Р В Р’ВµР РЋР вЂљР В Р вЂ¦Р В Р’В°",
                    "Р В РЎв„ўР РЋР вЂљР В РЎвЂР В Р вЂ Р В Р’В°Р В Р вЂ Р В РЎвЂў-Р РЋРІР‚РЋР В Р’ВµР РЋР вЂљР В Р вЂ Р В РЎвЂўР В Р вЂ¦Р В Р’В° Р РЋРІвЂљВ¬Р В РЎвЂўР В Р вЂ Р В РЎвЂќР В РЎвЂўР В Р вЂ Р В Р’В° Р В РЎвЂ”Р РЋРІР‚вЂњР В РўвЂР В РЎвЂќР В Р’В»Р В Р’В°Р В РўвЂР В РЎвЂќР В Р’В°",
                    "Р В РЎвЂ™Р РЋР С“Р В РЎвЂР В РЎВР В Р’ВµР РЋРІР‚С™Р РЋР вЂљР В РЎвЂР РЋРІР‚РЋР В Р вЂ¦Р РЋРІР‚вЂњ Р В Р’В±Р В Р’В»Р В РЎвЂР РЋР С“Р В РЎвЂќР В Р’В°Р В Р вЂ Р В РЎвЂќР В РЎвЂ YKK",
                    "Р В Р’В§Р В РЎвЂўР РЋРІР‚С™Р В РЎвЂР РЋР вЂљР В РЎвЂ Р В Р’В·Р В РЎвЂўР В Р вЂ Р В Р вЂ¦Р РЋРІР‚вЂњР РЋРІвЂљВ¬Р В Р вЂ¦Р РЋРІР‚вЂњ Р В РЎвЂќР В РЎвЂР РЋРІвЂљВ¬Р В Р’ВµР В Р вЂ¦Р РЋРІР‚вЂњ",
                    "Р В РЎвЂєР В РўвЂР В Р вЂ¦Р В Р’В° Р В РЎвЂ”Р РЋР вЂљР В РЎвЂР РЋРІР‚В¦Р В РЎвЂўР В Р вЂ Р В Р’В°Р В Р вЂ¦Р В Р’В° Р В Р вЂ Р В Р вЂ¦Р РЋРЎвЂњР РЋРІР‚С™Р РЋР вЂљР РЋРІР‚вЂњР РЋРІвЂљВ¬Р В Р вЂ¦Р РЋР РЏ Р В РЎвЂќР В РЎвЂР РЋРІвЂљВ¬Р В Р’ВµР В Р вЂ¦Р РЋР РЏ"
                ],
    "care":  [
                 "Р В РЎС›Р РЋРІР‚вЂњР В Р’В»Р РЋР Р‰Р В РЎвЂќР В РЎвЂ Р В РЎвЂ”Р РЋР вЂљР В РЎвЂўР РЋРІР‚С›Р В Р’ВµР РЋР С“Р РЋРІР‚вЂњР В РІвЂћвЂ“Р В Р вЂ¦Р В Р’Вµ Р РЋРІР‚РЋР В РЎвЂР РЋРІР‚В°Р В Р’ВµР В Р вЂ¦Р В Р вЂ¦Р РЋР РЏ Р РЋРІвЂљВ¬Р В РЎвЂќР РЋРІР‚вЂњР РЋР вЂљР В РЎвЂ",
                 "Р В РІР‚вЂќР В Р’В±Р В Р’ВµР РЋР вЂљР РЋРІР‚вЂњР В РЎвЂ“Р В Р’В°Р РЋРІР‚С™Р В РЎвЂ Р В Р вЂ¦Р В Р’В° Р В РЎВ\u0027Р РЋР РЏР В РЎвЂќР В РЎвЂР РЋРІР‚В¦ Р В РЎвЂ”Р В Р’В»Р РЋРІР‚вЂњР РЋРІР‚РЋР В РЎвЂќР В Р’В°Р РЋРІР‚В¦",
                 "Р В РЎв„ўР В РЎвЂўР В Р вЂ¦Р В РўвЂР В РЎвЂР РЋРІР‚В Р РЋРІР‚вЂњР В РЎвЂўР В Р вЂ¦Р РЋРЎвЂњР В Р вЂ Р В Р’В°Р РЋРІР‚С™Р В РЎвЂ Р РЋРІвЂљВ¬Р В РЎвЂќР РЋРІР‚вЂњР РЋР вЂљР РЋР РЏР В Р вЂ¦Р В РЎвЂР В РЎВ Р В Р’В±Р В Р’В°Р В Р’В»Р РЋР Р‰Р В Р’В·Р В Р’В°Р В РЎВР В РЎвЂўР В РЎВ Р РЋРІР‚В°Р В РЎвЂўР В РЎвЂќР В Р вЂ Р В Р’В°Р РЋР вЂљР РЋРІР‚С™Р В Р’В°Р В Р’В»Р РЋР Р‰Р В Р вЂ¦Р В РЎвЂў"
             ],
    "reviews":  [
                    {
                        "id":  "3",
                        "author":  "Dante R.",
                        "rating":  4,
                        "title":  "Р В Р’В§Р РЋРЎвЂњР В РўвЂР В РЎвЂўР В Р вЂ Р В Р’В° Р РЋР вЂљР РЋРІР‚вЂњР РЋРІР‚РЋ",
                        "content":  "Р В РЎСџР РЋР вЂљР В РЎвЂР В РЎвЂ“Р В РЎвЂўР В Р’В»Р В РЎвЂўР В РЎВР РЋРІвЂљВ¬Р В Р’В»Р В РЎвЂР В Р вЂ Р В РЎвЂР В РІвЂћвЂ“ Р В РўвЂР В РЎвЂР В Р’В·Р В Р’В°Р В РІвЂћвЂ“Р В Р вЂ¦ Р РЋРІР‚вЂњ Р В Р вЂ Р РЋРІР‚вЂњР В РўвЂР В РЎВР РЋРІР‚вЂњР В Р вЂ¦Р В Р вЂ¦Р В Р’В° Р РЋР РЏР В РЎвЂќР РЋРІР‚вЂњР РЋР С“Р РЋРІР‚С™Р РЋР Р‰. Р В РІР‚вЂќР В Р вЂ¦Р РЋР РЏР В Р вЂ  Р В Р’В·Р РЋРІР‚вЂњР РЋР вЂљР В РЎвЂќР РЋРЎвЂњ Р РЋРІР‚РЋР В Р’ВµР РЋР вЂљР В Р’ВµР В Р’В· Р В Р’В·Р В Р’В°Р РЋРІР‚С™Р РЋР вЂљР В РЎвЂР В РЎВР В РЎвЂќР РЋРЎвЂњ Р В РўвЂР В РЎвЂўР РЋР С“Р РЋРІР‚С™Р В Р’В°Р В Р вЂ Р В РЎвЂќР В РЎвЂ, Р В Р’В°Р В Р’В»Р В Р’Вµ Р РЋР С“Р В Р’В°Р В РЎВ Р В Р вЂ Р В РЎвЂР РЋР вЂљР РЋРІР‚вЂњР В Р’В± Р В РЎвЂ”Р В Р’ВµР РЋР вЂљР В Р’ВµР В Р вЂ Р В Р’ВµР РЋР вЂљР РЋРІвЂљВ¬Р РЋРЎвЂњР РЋРІР‚Сњ Р В Р вЂ Р РЋР С“Р РЋРІР‚вЂњ Р В РЎвЂўР РЋРІР‚РЋР РЋРІР‚вЂњР В РЎвЂќР РЋРЎвЂњР В Р вЂ Р В Р’В°Р В Р вЂ¦Р В Р вЂ¦Р РЋР РЏ.",
                        "date":  "2024-01-05",
                        "verified":  true
                    }
                ],
    "image1":  "https://images.pexels.com/photos/1126964/pexels-photo-1126964.jpeg?auto=compress\u0026cs=tinysrgb\u0026w=800",
    "image2":  "https://images.pexels.com/photos/10409446/pexels-photo-10409446.jpeg?auto=compress\u0026cs=tinysrgb\u0026w=800",
    "image3":  "https://images.pexels.com/photos/16196537/pexels-photo-16196537.jpeg?auto=compress\u0026cs=tinysrgb\u0026w=800"
}